{
  "id": "b2b_legal_finance_ops",
  "name": "b2b_legal_finance_ops",
  "title": "B2B — Legal — Finance Ops",
  "description": "B2B, Legal pains and workflows around Finance Ops.",
  "version": 1,
  "enabled": true,
  "tags": [
    "b2b",
    "legal",
    "finance_ops"
  ],
  "default_queries": [
    "invoice approval bottleneck",
    "expense policy enforcement",
    "month end close automation",
    "Finance Ops",
    "Finance Ops pain",
    "Finance Ops bottleneck",
    "Finance Ops automation",
    "Finance Ops workflow",
    "Finance Ops tooling",
    "Finance Ops process",
    "Finance Ops best practices",
    "roadmap"
  ],
  "persona": "product_lead",
  "axes": {
    "audience": "b2b",
    "function": "legal"
  },
  "notes": "Generated deterministically from taxonomy (member=finance_ops, persona=product_lead)."
}
