{
  "id": "b2b_security_industry_agriculture_community",
  "name": "b2b_security_industry_agriculture_community",
  "title": "B2B — Security — Agriculture — Community",
  "description": "B2B, Security, Agriculture pains and workflows around Community.",
  "version": 1,
  "enabled": true,
  "tags": [
    "b2b",
    "security",
    "industry_agriculture",
    "community"
  ],
  "default_queries": [
    "engagement drop",
    "moderation overhead",
    "content calendar chaos",
    "Community",
    "Community pain",
    "Community bottleneck",
    "Community automation",
    "Community workflow",
    "Community tooling",
    "Community process",
    "Community best practices",
    "SEO"
  ],
  "persona": "marketer",
  "axes": {
    "audience": "b2b",
    "function": "security",
    "industry": "industry_agriculture"
  },
  "notes": "Generated deterministically from taxonomy (member=community, persona=marketer)."
}
