{
  "id": "b2b_marketing_industry_ecommerce_frontend",
  "name": "b2b_marketing_industry_ecommerce_frontend",
  "title": "B2B — Marketing — Ecommerce — Frontend",
  "description": "B2B, Marketing, Ecommerce pains and workflows around Frontend.",
  "version": 1,
  "enabled": true,
  "tags": [
    "b2b",
    "marketing",
    "industry_ecommerce",
    "frontend"
  ],
  "default_queries": [
    "bundle size regression",
    "hydration errors",
    "design system drift",
    "Frontend",
    "Frontend pain",
    "Frontend bottleneck",
    "Frontend automation",
    "Frontend workflow",
    "Frontend tooling",
    "Frontend process",
    "Frontend best practices",
    "process"
  ],
  "persona": "ops_manager",
  "axes": {
    "audience": "b2b",
    "function": "marketing",
    "industry": "industry_ecommerce"
  },
  "notes": "Generated deterministically from taxonomy (member=frontend, persona=ops_manager)."
}
