{
  "id": "b2b_marketing_industry_healthcare_devops",
  "name": "b2b_marketing_industry_healthcare_devops",
  "title": "B2B — Marketing — Healthcare — DevOps",
  "description": "B2B, Marketing, Healthcare pains and workflows around DevOps.",
  "version": 1,
  "enabled": true,
  "tags": [
    "b2b",
    "marketing",
    "industry_healthcare",
    "devops"
  ],
  "default_queries": [
    "deploy failures",
    "ci flaky tests",
    "infra drift terraform",
    "DevOps",
    "DevOps pain",
    "DevOps bottleneck",
    "DevOps automation",
    "DevOps workflow",
    "DevOps tooling",
    "DevOps process",
    "DevOps best practices",
    "debug"
  ],
  "persona": "engineer",
  "axes": {
    "audience": "b2b",
    "function": "marketing",
    "industry": "industry_healthcare"
  },
  "notes": "Generated deterministically from taxonomy (member=devops, persona=engineer)."
}
