{
  "id": "b2b_product_industry_education_events",
  "name": "b2b_product_industry_education_events",
  "title": "B2B — Product — Education — Events",
  "description": "B2B, Product, Education pains and workflows around Events.",
  "version": 1,
  "enabled": true,
  "tags": [
    "b2b",
    "product",
    "industry_education",
    "events"
  ],
  "default_queries": [
    "lead capture workflow",
    "booth follow-up process",
    "event ROI tracking",
    "Events",
    "Events pain",
    "Events bottleneck",
    "Events automation",
    "Events workflow",
    "Events tooling",
    "Events process",
    "Events best practices",
    "process"
  ],
  "persona": "ops_manager",
  "axes": {
    "audience": "b2b",
    "function": "product",
    "industry": "industry_education"
  },
  "notes": "Generated deterministically from taxonomy (member=events, persona=ops_manager)."
}
