{
  "id": "b2b_legal_industry_energy_billing_ops",
  "name": "b2b_legal_industry_energy_billing_ops",
  "title": "B2B — Legal — Energy — Billing Ops",
  "description": "B2B, Legal, Energy pains and workflows around Billing Ops.",
  "version": 1,
  "enabled": true,
  "tags": [
    "b2b",
    "legal",
    "industry_energy",
    "billing_ops"
  ],
  "default_queries": [
    "billing disputes",
    "refund workflow pain",
    "invoice accuracy issues",
    "Billing Ops",
    "Billing Ops pain",
    "Billing Ops bottleneck",
    "Billing Ops automation",
    "Billing Ops workflow",
    "Billing Ops tooling",
    "Billing Ops process",
    "Billing Ops best practices",
    "MVP"
  ],
  "persona": "founder",
  "axes": {
    "audience": "b2b",
    "function": "legal",
    "industry": "industry_energy"
  },
  "notes": "Generated deterministically from taxonomy (member=billing_ops, persona=founder)."
}
