{
  "id": "b2b_legal_industry_construction_pricing",
  "name": "b2b_legal_industry_construction_pricing",
  "title": "B2B — Legal — Construction — Pricing & Packaging",
  "description": "B2B, Legal, Construction pains and workflows around Pricing & Packaging.",
  "version": 1,
  "enabled": true,
  "tags": [
    "b2b",
    "legal",
    "industry_construction",
    "pricing"
  ],
  "default_queries": [
    "discount approvals",
    "pricing page confusion",
    "plan mismatch churn",
    "Pricing & Packaging",
    "Pricing & Packaging pain",
    "Pricing & Packaging bottleneck",
    "Pricing & Packaging automation",
    "Pricing & Packaging workflow",
    "Pricing & Packaging tooling",
    "Pricing & Packaging process",
    "Pricing & Packaging best practices",
    "process"
  ],
  "persona": "ops_manager",
  "axes": {
    "audience": "b2b",
    "function": "legal",
    "industry": "industry_construction"
  },
  "notes": "Generated deterministically from taxonomy (member=pricing, persona=ops_manager)."
}
