{
  "id": "b2b_data_industry_legal_backend",
  "name": "b2b_data_industry_legal_backend",
  "title": "B2B — Data — Legal Services — Backend",
  "description": "B2B, Data, Legal Services pains and workflows around Backend.",
  "version": 1,
  "enabled": true,
  "tags": [
    "b2b",
    "data",
    "industry_legal",
    "backend"
  ],
  "default_queries": [
    "API performance",
    "database bottlenecks",
    "queue reliability issues",
    "Backend",
    "Backend pain",
    "Backend bottleneck",
    "Backend automation",
    "Backend workflow",
    "Backend tooling",
    "Backend process",
    "Backend best practices",
    "cashflow"
  ],
  "persona": "finance_lead",
  "axes": {
    "audience": "b2b",
    "function": "data",
    "industry": "industry_legal"
  },
  "notes": "Generated deterministically from taxonomy (member=backend, persona=finance_lead)."
}
