{
  "id": "b2b_sales_industry_real_estate_devops",
  "name": "b2b_sales_industry_real_estate_devops",
  "title": "B2B — Sales — Real Estate — DevOps",
  "description": "B2B, Sales, Real Estate pains and workflows around DevOps.",
  "version": 1,
  "enabled": true,
  "tags": [
    "b2b",
    "sales",
    "industry_real_estate",
    "devops"
  ],
  "default_queries": [
    "deploy failures",
    "ci flaky tests",
    "infra drift terraform",
    "DevOps",
    "DevOps pain",
    "DevOps bottleneck",
    "DevOps automation",
    "DevOps workflow",
    "DevOps tooling",
    "DevOps process",
    "DevOps best practices",
    "process"
  ],
  "persona": "ops_manager",
  "axes": {
    "audience": "b2b",
    "function": "sales",
    "industry": "industry_real_estate"
  },
  "notes": "Generated deterministically from taxonomy (member=devops, persona=ops_manager)."
}
