{
  "id": "b2b_legal_industry_ecommerce_lifecycle",
  "name": "b2b_legal_industry_ecommerce_lifecycle",
  "title": "B2B — Legal — Ecommerce — Lifecycle",
  "description": "B2B, Legal, Ecommerce pains and workflows around Lifecycle.",
  "version": 1,
  "enabled": true,
  "tags": [
    "b2b",
    "legal",
    "industry_ecommerce",
    "lifecycle"
  ],
  "default_queries": [
    "activation drop-off",
    "email deliverability issues",
    "onboarding sequence gaps",
    "Lifecycle",
    "Lifecycle pain",
    "Lifecycle bottleneck",
    "Lifecycle automation",
    "Lifecycle workflow",
    "Lifecycle tooling",
    "Lifecycle process",
    "Lifecycle best practices",
    "MVP"
  ],
  "persona": "founder",
  "axes": {
    "audience": "b2b",
    "function": "legal",
    "industry": "industry_ecommerce"
  },
  "notes": "Generated deterministically from taxonomy (member=lifecycle, persona=founder)."
}
