{
  "id": "b2b_industry_fintech_devops",
  "name": "b2b_industry_fintech_devops",
  "title": "B2B — Fintech — DevOps",
  "description": "B2B, Fintech pains and workflows around DevOps.",
  "version": 1,
  "enabled": true,
  "tags": [
    "b2b",
    "industry_fintech",
    "devops"
  ],
  "default_queries": [
    "deploy failures",
    "ci flaky tests",
    "infra drift terraform",
    "DevOps",
    "DevOps pain",
    "DevOps bottleneck",
    "DevOps automation",
    "DevOps workflow",
    "DevOps tooling",
    "DevOps process",
    "DevOps best practices",
    "pipeline"
  ],
  "persona": "sales_rep",
  "axes": {
    "audience": "b2b",
    "industry": "industry_fintech"
  },
  "notes": "Generated deterministically from taxonomy (member=devops, persona=sales_rep)."
}
