{
  "id": "b2b_sales_industry_hospitality_observability",
  "name": "b2b_sales_industry_hospitality_observability",
  "title": "B2B — Sales — Hospitality — Observability",
  "description": "B2B, Sales, Hospitality pains and workflows around Observability.",
  "version": 1,
  "enabled": true,
  "tags": [
    "b2b",
    "sales",
    "industry_hospitality",
    "observability"
  ],
  "default_queries": [
    "missing traces",
    "noisy alerts",
    "SLO burn rate confusion",
    "Observability",
    "Observability pain",
    "Observability bottleneck",
    "Observability automation",
    "Observability workflow",
    "Observability tooling",
    "Observability process",
    "Observability best practices",
    "pipeline"
  ],
  "persona": "sales_rep",
  "axes": {
    "audience": "b2b",
    "function": "sales",
    "industry": "industry_hospitality"
  },
  "notes": "Generated deterministically from taxonomy (member=observability, persona=sales_rep)."
}
