{
  "id": "b2c_ops_support",
  "name": "b2c_ops_support",
  "title": "B2C — Operations: Customer Support",
  "description": "B2C teams dealing with customer support workflows, tooling, and operational friction.",
  "version": 1,
  "enabled": true,
  "tags": [
    "b2c",
    "ops",
    "ops:support"
  ],
  "default_queries": [
    "support tickets",
    "support tickets workflow",
    "support tickets tooling",
    "support tickets automation",
    "support tickets pain points",
    "support tickets process"
  ],
  "defaults": {
    "language_allowlist": [
      "en"
    ],
    "min_signal_quality": 0.2
  },
  "ingestion": {
    "sources": [
      {
        "name": "reddit",
        "limit": 80
      },
      {
        "name": "hackernews",
        "limit": 80
      },
      {
        "name": "indiehackers",
        "limit": 80
      }
    ]
  },
  "taxonomy": {
    "segment": "b2c",
    "function": "ops",
    "subdomain": "support"
  }
}
