{
  "id": "b2c_security_industry_supply_chain_partners",
  "name": "b2c_security_industry_supply_chain_partners",
  "title": "B2C — Security — Supply Chain — Partnerships",
  "description": "B2C, Security, Supply Chain pains and workflows around Partnerships.",
  "version": 1,
  "enabled": true,
  "tags": [
    "b2c",
    "security",
    "industry_supply_chain",
    "partners"
  ],
  "default_queries": [
    "co-sell motion confusion",
    "partner onboarding",
    "lead sharing process",
    "Partnerships",
    "Partnerships pain",
    "Partnerships bottleneck",
    "Partnerships automation",
    "Partnerships workflow",
    "Partnerships tooling",
    "Partnerships process",
    "Partnerships best practices",
    "debug"
  ],
  "persona": "engineer",
  "axes": {
    "audience": "b2c",
    "function": "security",
    "industry": "industry_supply_chain"
  },
  "notes": "Generated deterministically from taxonomy (member=partners, persona=engineer)."
}
