{
  "id": "b2c_security_industry_media_community",
  "name": "b2c_security_industry_media_community",
  "title": "B2C — Security — Media — Community",
  "description": "B2C, Security, Media pains and workflows around Community.",
  "version": 1,
  "enabled": true,
  "tags": [
    "b2c",
    "security",
    "industry_media",
    "community"
  ],
  "default_queries": [
    "engagement drop",
    "moderation overhead",
    "content calendar chaos",
    "Community",
    "Community pain",
    "Community bottleneck",
    "Community automation",
    "Community workflow",
    "Community tooling",
    "Community process",
    "Community best practices",
    "compliance"
  ],
  "persona": "security_lead",
  "axes": {
    "audience": "b2c",
    "function": "security",
    "industry": "industry_media"
  },
  "notes": "Generated deterministically from taxonomy (member=community, persona=security_lead)."
}
