{
  "id": "b2c_sales_industry_hospitality_platform_eng",
  "name": "b2c_sales_industry_hospitality_platform_eng",
  "title": "B2C — Sales — Hospitality — Platform Engineering",
  "description": "B2C, Sales, Hospitality pains and workflows around Platform Engineering.",
  "version": 1,
  "enabled": true,
  "tags": [
    "b2c",
    "sales",
    "industry_hospitality",
    "platform_eng"
  ],
  "default_queries": [
    "internal developer portal pain",
    "golden paths platform",
    "service scaffolding",
    "Platform Engineering",
    "Platform Engineering pain",
    "Platform Engineering bottleneck",
    "Platform Engineering automation",
    "Platform Engineering workflow",
    "Platform Engineering tooling",
    "Platform Engineering process",
    "Platform Engineering best practices",
    "MVP"
  ],
  "persona": "founder",
  "axes": {
    "audience": "b2c",
    "function": "sales",
    "industry": "industry_hospitality"
  },
  "notes": "Generated deterministically from taxonomy (member=platform_eng, persona=founder)."
}
