{
  "id": "hr_industry_legal_brand",
  "name": "hr_industry_legal_brand",
  "title": "HR — Legal Services — Brand",
  "description": "HR, Legal Services pains and workflows around Brand.",
  "version": 1,
  "enabled": true,
  "tags": [
    "hr",
    "industry_legal",
    "brand"
  ],
  "default_queries": [
    "positioning unclear",
    "brand consistency",
    "messaging fragmentation",
    "Brand",
    "Brand pain",
    "Brand bottleneck",
    "Brand automation",
    "Brand workflow",
    "Brand tooling",
    "Brand process",
    "Brand best practices",
    "compliance"
  ],
  "persona": "security_lead",
  "axes": {
    "function": "hr",
    "industry": "industry_legal"
  },
  "notes": "Generated deterministically from taxonomy (member=brand, persona=security_lead)."
}
