{
  "id": "industry_healthcare_frontend",
  "name": "industry_healthcare_frontend",
  "title": "Healthcare — Frontend",
  "description": "Healthcare pains and workflows around Frontend.",
  "version": 1,
  "enabled": true,
  "tags": [
    "industry_healthcare",
    "frontend"
  ],
  "default_queries": [
    "bundle size regression",
    "hydration errors",
    "design system drift",
    "Frontend",
    "Frontend pain",
    "Frontend bottleneck",
    "Frontend automation",
    "Frontend workflow",
    "Frontend tooling",
    "Frontend process",
    "Frontend best practices",
    "process"
  ],
  "persona": "ops_manager",
  "axes": {
    "industry": "industry_healthcare"
  },
  "notes": "Generated deterministically from taxonomy (member=frontend, persona=ops_manager)."
}
