{
  "id": "product_industry_construction_pricing",
  "name": "product_industry_construction_pricing",
  "title": "Product — Construction — Pricing & Packaging",
  "description": "Product, Construction pains and workflows around Pricing & Packaging.",
  "version": 1,
  "enabled": true,
  "tags": [
    "product",
    "industry_construction",
    "pricing"
  ],
  "default_queries": [
    "discount approvals",
    "pricing page confusion",
    "plan mismatch churn",
    "Pricing & Packaging",
    "Pricing & Packaging pain",
    "Pricing & Packaging bottleneck",
    "Pricing & Packaging automation",
    "Pricing & Packaging workflow",
    "Pricing & Packaging tooling",
    "Pricing & Packaging process",
    "Pricing & Packaging best practices",
    "MVP"
  ],
  "persona": "founder",
  "axes": {
    "function": "product",
    "industry": "industry_construction"
  },
  "notes": "Generated deterministically from taxonomy (member=pricing, persona=founder)."
}
