{
  "id": "product_industry_healthcare_paid",
  "name": "product_industry_healthcare_paid",
  "title": "Product — Healthcare — Paid Acquisition",
  "description": "Product, Healthcare pains and workflows around Paid Acquisition.",
  "version": 1,
  "enabled": true,
  "tags": [
    "product",
    "industry_healthcare",
    "paid"
  ],
  "default_queries": [
    "CAC rising",
    "attribution mismatch",
    "creative fatigue",
    "Paid Acquisition",
    "Paid Acquisition pain",
    "Paid Acquisition bottleneck",
    "Paid Acquisition automation",
    "Paid Acquisition workflow",
    "Paid Acquisition tooling",
    "Paid Acquisition process",
    "Paid Acquisition best practices",
    "process"
  ],
  "persona": "ops_manager",
  "axes": {
    "function": "product",
    "industry": "industry_healthcare"
  },
  "notes": "Generated deterministically from taxonomy (member=paid, persona=ops_manager)."
}
