{
  "id": "sales_industry_it_services_events",
  "name": "sales_industry_it_services_events",
  "title": "Sales — IT Services (MSP) — Events",
  "description": "Sales, IT Services (MSP) pains and workflows around Events.",
  "version": 1,
  "enabled": true,
  "tags": [
    "sales",
    "industry_it_services",
    "events"
  ],
  "default_queries": [
    "lead capture workflow",
    "booth follow-up process",
    "event ROI tracking",
    "Events",
    "Events pain",
    "Events bottleneck",
    "Events automation",
    "Events workflow",
    "Events tooling",
    "Events process",
    "Events best practices",
    "MVP"
  ],
  "persona": "founder",
  "axes": {
    "function": "sales",
    "industry": "industry_it_services"
  },
  "notes": "Generated deterministically from taxonomy (member=events, persona=founder)."
}
